flashrnn/__init__.py
flashrnn/autotune/__init__.py
flashrnn/autotune/caching.py
flashrnn/autotune/constrint.py
flashrnn/autotune/runner.py
flashrnn/autotune/submit.py
flashrnn/flashrnn/__init__.py
flashrnn/flashrnn/cuda_init.py
flashrnn/flashrnn/cuda_init_parametric.py
flashrnn/flashrnn/flashrnn.py
flashrnn/flashrnn/alternating/elman_pointwise.cu
flashrnn/flashrnn/alternating/flashrnn.cc
flashrnn/flashrnn/alternating/flashrnn.h
flashrnn/flashrnn/alternating/flashrnn_backward.cu
flashrnn/flashrnn/alternating/flashrnn_backward_cut.cu
flashrnn/flashrnn/alternating/flashrnn_forward.cu
flashrnn/flashrnn/alternating/flashrnn_pointwise.cuh
flashrnn/flashrnn/alternating/gru_pointwise.cu
flashrnn/flashrnn/alternating/lstm_pointwise.cu
flashrnn/flashrnn/alternating/slstm_pointwise.cu
flashrnn/flashrnn/fused/__init__.py
flashrnn/flashrnn/fused/elman_fused_pointwise.cuh
flashrnn/flashrnn/fused/flashrnn.cc
flashrnn/flashrnn/fused/flashrnn.h
flashrnn/flashrnn/fused/flashrnn_fused_backward.cu
flashrnn/flashrnn/fused/flashrnn_fused_backward_cut.cu
flashrnn/flashrnn/fused/flashrnn_fused_forward.cu
flashrnn/flashrnn/fused/flashrnn_fused_pointwise_base.cuh
flashrnn/flashrnn/fused/gru_fused_pointwise.cuh
flashrnn/flashrnn/fused/lstm_fused_pointwise.cuh
flashrnn/flashrnn/fused/slstm_fused_pointwise.cuh
flashrnn/flashrnn/gpu_info/__init__.py
flashrnn/flashrnn/gpu_info/assign_struct.py
flashrnn/flashrnn/gpu_info/defs_cudaDeviceProperties.cc
flashrnn/flashrnn/gpu_info/gpu_info.cc
flashrnn/flashrnn/gpu_info/gpu_info.cu
flashrnn/flashrnn/gpu_info/gpu_info.h
flashrnn/flashrnn/gpu_info/gpu_info.py
flashrnn/flashrnn/gpu_info/gpu_info_test.cc
flashrnn/flashrnn/triton_fused/__init__.py
flashrnn/flashrnn/triton_fused/fwbw.py
flashrnn/flashrnn/triton_fused/lstm_bw.py
flashrnn/flashrnn/triton_fused/lstm_fw.py
flashrnn/flashrnn/triton_fused/slstm_bw.py
flashrnn/flashrnn/triton_fused/slstm_fw.py
flashrnn/flashrnn/triton_fused/triton_utils.py
flashrnn/flashrnn/util/blas.cu
flashrnn-1.0.3.dist-info/LICENSE
flashrnn-1.0.3.dist-info/METADATA
flashrnn-1.0.3.dist-info/WHEEL
flashrnn-1.0.3.dist-info/top_level.txt
flashrnn-1.0.3.dist-info/RECORD
