Metadata-Version: 2.1
Name: flashrnn
Version: 1.0.3
Summary: FlashRNN: Optimizing Traditional RNNs on Modern Hardware
Author-email: Korbinian Pöppel <korbinian.poeppel@nx-ai.com>, Maximilian Beck <maximilian.beck@nx-ai.com>
Project-URL: Homepage, https://github.com/NX-AI/flashrnn
Project-URL: Issues, https://github.com/NX-AI/flashrnn/issues
Classifier: Programming Language :: Python :: 3
Classifier: Operating System :: OS Independent
Requires-Python: >=3.8
License-File: LICENSE
Requires-Dist: torch
Requires-Dist: einops
Requires-Dist: triton
Requires-Dist: ninja
